S2Generator/__init__.py
S2Generator/base.py
S2Generator/encoders.py
S2Generator/generators.py
S2Generator/excitation/__init__.py
S2Generator/excitation/_interface.py
S2Generator/excitation/autoregressive_moving_average.py
S2Generator/excitation/base_excitation.py
S2Generator/excitation/forecast_pfn.py
S2Generator/excitation/intrinsic_mode_functions.py
S2Generator/excitation/kernel_synth.py
S2Generator/excitation/mixed_distribution.py
S2Generator/params/__init__.py
S2Generator/params/series_params.py
S2Generator/params/symbol_params.py
S2Generator/utils/__init__.py
S2Generator/utils/_decomposition.py
S2Generator/utils/_print_status.py
S2Generator/utils/_smooth.py
S2Generator/utils/_tools.py
S2Generator/utils/_wasserstein_distance.py
S2Generator/utils/print_symbol.py
S2Generator/utils/visualization.py
s2generator-0.0.3.dist-info/licenses/LICENSE
tests/__init__.py
tests/test_all.py
tests/test_arma.py
tests/test_base_excitation.py
tests/test_forecast_pfn.py
tests/test_intrinsic_mode_functions.py
tests/test_kernel_synth.py
tests/test_mixed_distribution.py
tests/test_series_params.py
tests/test_stl.py
tests/test_symbol_params.py
tests/test_tools.py
tests/test_wasserstein.py
s2generator-0.0.3.dist-info/METADATA
s2generator-0.0.3.dist-info/WHEEL
s2generator-0.0.3.dist-info/top_level.txt
s2generator-0.0.3.dist-info/RECORD
