Metadata-Version: 2.4
Name: S2Generator
Version: 0.0.3
Summary: A series-symbol (S2) dual-modality data generation mechanism, enabling the unrestricted creation of high-quality time series data paired with corresponding symbolic representations.
Home-page: https://github.com/wwhenxuan/S2Generator
Author: whenxuan, johnfan12, changewam
Author-email: wwhenxuan@gmail.com
Keywords: Time Series,Data Generation
Classifier: Development Status :: 3 - Alpha
Classifier: Intended Audience :: Science/Research
Classifier: Topic :: Scientific/Engineering :: Mathematics
Classifier: Topic :: Scientific/Engineering :: Artificial Intelligence
Classifier: License :: OSI Approved :: MIT License
Classifier: Programming Language :: Python :: 3.9
Classifier: Programming Language :: Python :: 3.10
Classifier: Programming Language :: Python :: 3.11
Requires-Python: >=3.9
License-File: LICENSE
Requires-Dist: numpy>=1.24.4
Requires-Dist: scipy>=1.14.1
Requires-Dist: matplotlib>=3.9.2
Requires-Dist: scikit-learn>=1.2.2
Requires-Dist: colorama>=0.4.6
Requires-Dist: pysdkit>=0.4.21
Dynamic: author
Dynamic: author-email
Dynamic: classifier
Dynamic: description
Dynamic: description-content-type
Dynamic: home-page
Dynamic: keywords
Dynamic: license-file
Dynamic: requires-dist
Dynamic: requires-python
Dynamic: summary
